README.rst
setup.py
fieldops/__init__.py
fieldops/fieldops
fieldops/fieldopsconn.py
fieldops.egg-info/PKG-INFO
fieldops.egg-info/SOURCES.txt
fieldops.egg-info/dependency_links.txt
fieldops.egg-info/requires.txt
fieldops.egg-info/top_level.txt