Metadata-Version: 2.1
Name: fieldops
Version: 0.0.5
Summary: CLI and library for interacting with FieldOps api
Home-page: https://fieldops.readthedocs.io/en/latest/
Author: Jason Berger
Author-email: berge472@gmail.com
License: UNKNOWN
Platform: UNKNOWN
Classifier: Programming Language :: Python :: 3
Classifier: License :: OSI Approved :: MIT License
Classifier: Operating System :: OS Independent
